feerci.cpython-35m-x86_64-linux-gnu.so
feerci-0.2.0.dist-info/METADATA
feerci-0.2.0.dist-info/WHEEL
feerci-0.2.0.dist-info/top_level.txt
feerci-0.2.0.dist-info/RECORD
tests/test_feer.py
tests/test_feerci.py
tests/__init__.py
