Metadata-Version: 2.1
Name: feerci
Version: 0.2.0
Summary: FEERCI: A python package for EER confidence intervals 
Home-page: https://github.com/feerci/feerci
Author: UNKNOWN
Author-email: UNKNOWN
License: UNKNOWN
Keywords: EER,Confidence Interval,feerci,feer,biometrics
Platform: UNKNOWN
Classifier: Development Status :: 3 - Alpha
Classifier: Intended Audience :: Science/Research
Classifier: License :: OSI Approved :: MIT License
Classifier: Programming Language :: Python :: 3.5
Requires-Dist: numpy (>=1.7)
Requires-Dist: Cython
